cli.py
cli_integration.py
jira_comments_script.py
slack_integration.py
tableau_integration.py
jiraquest-1.0.0.dist-info/LICENSE
jiraquest-1.0.0.dist-info/METADATA
jiraquest-1.0.0.dist-info/WHEEL
jiraquest-1.0.0.dist-info/entry_points.txt
jiraquest-1.0.0.dist-info/top_level.txt
jiraquest-1.0.0.dist-info/RECORD
